goinpy/__init__.py
goinpy/goinpy.py
goinpy-0.4.dist-info/LICENSE
goinpy-0.4.dist-info/METADATA
goinpy-0.4.dist-info/WHEEL
goinpy-0.4.dist-info/top_level.txt
goinpy-0.4.dist-info/RECORD
