Metadata-Version: 2.1
Name: goinpy
Version: 0.4
Summary: Use Golang functions inside Python code
Home-page: http://github.com/hermanTenuki/goinpy/
Author: Herman Schechkin (hermanTenuki)
Author-email: itseasy322@gmail.com
License: MIT
Platform: UNKNOWN
Classifier: Development Status :: 3 - Alpha
Classifier: Intended Audience :: Developers
Classifier: License :: OSI Approved :: MIT License
Classifier: Programming Language :: Python :: 3
Classifier: Operating System :: OS Independent
Requires-Python: >=3.6
